{
  "main": {
    "id": "9f9b71065bd686ed",
    "type": "split",
    "children": [
      {
        "id": "a68b66bb5e8db779",
        "type": "tabs",
        "children": [
          {
            "id": "f315c61447bca4ea",
            "type": "leaf",
            "state": {
              "type": "markdown",
              "state": {
                "file": "AI/Dialog gpt.md",
                "mode": "source",
                "source": false
              },
              "icon": "lucide-file",
              "title": "Dialog gpt"
            }
          },
          {
            "id": "b677884a51ffd0e9",
            "type": "leaf",
            "state": {
              "type": "markdown",
              "state": {
                "file": "AI/amaydle npc-dialogue.md",
                "mode": "source",
                "source": false
              },
              "icon": "lucide-file",
              "title": "amaydle npc-dialogue"
            }
          },
          {
            "id": "1edc4060786a1893",
            "type": "leaf",
            "state": {
              "type": "markdown",
              "state": {
                "file": "AI/미래.md",
                "mode": "source",
                "source": false
              },
              "icon": "lucide-file",
              "title": "미래"
            }
          },
          {
            "id": "6e5766c52101cd90",
            "type": "leaf",
            "state": {
              "type": "markdown",
              "state": {
                "file": "확통.md",
                "mode": "source",
                "source": false
              },
              "icon": "lucide-file",
              "title": "확통"
            }
          },
          {
            "id": "38d4316f735c221b",
            "type": "leaf",
            "state": {
              "type": "markdown",
              "state": {
                "file": "AI/kist.md",
                "mode": "source",
                "source": false
              },
              "icon": "lucide-file",
              "title": "kist"
            }
          },
          {
            "id": "a8777f590ff8a332",
            "type": "leaf",
            "state": {
              "type": "markdown",
              "state": {
                "file": "AI/fine-tuning.md",
                "mode": "source",
                "source": false
              },
              "icon": "lucide-file",
              "title": "fine-tuning"
            }
          },
          {
            "id": "63d4cec713620d2b",
            "type": "leaf",
            "state": {
              "type": "markdown",
              "state": {
                "file": "model/DETR.md",
                "mode": "source",
                "source": false
              },
              "icon": "lucide-file",
              "title": "DETR"
            }
          }
        ],
        "currentTab": 6
      }
    ],
    "direction": "vertical"
  },
  "left": {
    "id": "41947c0fdec294c3",
    "type": "split",
    "children": [
      {
        "id": "b8810c5e9d6f8c4b",
        "type": "tabs",
        "children": [
          {
            "id": "274cfd5e0c0e8e16",
            "type": "leaf",
            "state": {
              "type": "file-explorer",
              "state": {
                "sortOrder": "alphabetical",
                "autoReveal": false
              },
              "icon": "lucide-folder-closed",
              "title": "파일 탐색기"
            }
          },
          {
            "id": "4a758af285140fe9",
            "type": "leaf",
            "state": {
              "type": "search",
              "state": {
                "query": "tag:#10장퀴즈",
                "matchingCase": false,
                "explainSearch": false,
                "collapseAll": false,
                "extraContext": false,
                "sortOrder": "alphabetical"
              },
              "icon": "lucide-search",
              "title": "검색"
            }
          },
          {
            "id": "c337d33aaf43ac54",
            "type": "leaf",
            "state": {
              "type": "bookmarks",
              "state": {},
              "icon": "lucide-bookmark",
              "title": "북마크"
            }
          }
        ]
      }
    ],
    "direction": "horizontal",
    "width": 200
  },
  "right": {
    "id": "f7361d466fb9ae75",
    "type": "split",
    "children": [
      {
        "id": "9d981705f87abcba",
        "type": "tabs",
        "children": [
          {
            "id": "b5cdd43cf0b88908",
            "type": "leaf",
            "state": {
              "type": "backlink",
              "state": {
                "file": "AI SW 전문가 튜토리얼/2차.md",
                "collapseAll": false,
                "extraContext": false,
                "sortOrder": "alphabetical",
                "showSearch": false,
                "searchQuery": "",
                "backlinkCollapsed": false,
                "unlinkedCollapsed": true
              },
              "icon": "links-coming-in",
              "title": "2차 의 백링크"
            }
          },
          {
            "id": "00c1ccd041ac11af",
            "type": "leaf",
            "state": {
              "type": "outgoing-link",
              "state": {
                "file": "AI SW 전문가 튜토리얼/2차.md",
                "linksCollapsed": false,
                "unlinkedCollapsed": true
              },
              "icon": "links-going-out",
              "title": "2차 의 나가는 링크"
            }
          },
          {
            "id": "7137fdd3cbdbb6ee",
            "type": "leaf",
            "state": {
              "type": "tag",
              "state": {
                "sortOrder": "frequency",
                "useHierarchy": true,
                "showSearch": false,
                "searchQuery": ""
              },
              "icon": "lucide-tags",
              "title": "태그"
            }
          },
          {
            "id": "e919f8ddabb1d9d8",
            "type": "leaf",
            "state": {
              "type": "outline",
              "state": {
                "file": "대학강의/OSS/OSS란?.md",
                "followCursor": false,
                "showSearch": false,
                "searchQuery": ""
              },
              "icon": "lucide-list",
              "title": "OSS란? 의 개요"
            }
          },
          {
            "id": "f3bbdafd710b5dca",
            "type": "leaf",
            "state": {
              "type": "calendar",
              "state": {},
              "icon": "calendar-with-checkmark",
              "title": "Calendar"
            }
          },
          {
            "id": "dac1545506f8b0ad",
            "type": "leaf",
            "state": {
              "type": "git-view",
              "state": {},
              "icon": "git-pull-request",
              "title": "Source Control"
            }
          }
        ],
        "currentTab": 5
      }
    ],
    "direction": "horizontal",
    "width": 200
  },
  "left-ribbon": {
    "hiddenItems": {
      "switcher:빠른 전환기 열기": false,
      "graph:그래프 뷰 열기": false,
      "canvas:새 캔버스 만들기": false,
      "daily-notes:오늘의 일일 노트 열기": false,
      "templates:템플릿 삽입": false,
      "command-palette:명령어 팔레트 열기": false,
      "obsidian-git:Open Git source control": false,
      "periodic-notes:Open today": false
    }
  },
  "active": "63d4cec713620d2b",
  "lastOpenFiles": [
    "AI/fine-tuning.md",
    "model/DETR.md",
    "model",
    "AI/kist.md",
    "AI/amaydle npc-dialogue.md",
    "AI/미래.md",
    "model/Faster R-CNN.md",
    "AI/semyung github.md",
    "model/Dialog gpt.md",
    "확통.md",
    "README.md",
    "Unity/Monobehaviur.md",
    "Unity/Component.md",
    "Unity/Animation.md",
    "Lang/python.md",
    "Lang/cpp.md",
    "AI",
    "대학강의/OSS/OSS란?.md",
    "대학강의/OSS/Github.md",
    "대학강의/객체지향/CPP.md",
    "Calendar/Daily/2025-06-12.md",
    "대학강의/데이터구조/자료구조.md",
    "대학강의/데이터구조/흐름.md",
    "대학강의/데이터구조/재귀.md",
    "Calendar/Daily/2025-06-06.md",
    "Calendar/Daily/2025-05-22.md",
    "대학강의/컴퓨터구조/컴퓨터 구조.md",
    "대학강의/문제해결프로그래밍/흐름.md",
    "무제.canvas",
    "AI SW 전문가 튜토리얼",
    "깃허브",
    "대학강의/객체지향",
    "Pasted image 20250313104200.png",
    "대학강의/OSS",
    "대학강의/컴퓨터구조",
    "Unity/무제",
    "Unity",
    "대학강의"
  ]
}